{
  "id": "motherduck-data-ingestion-nager",
  "name": "MotherDuck Data Ingestion - Nager",
  "nodes": [
    {
      "parameters": {
        "rule": {
          "interval": [
            {
              "triggerAtHour": 3
            }
          ]
        }
      },
      "id": "schedule-trigger",
      "name": "Schedule Trigger",
      "type": "n8n-nodes-base.scheduleTrigger",
      "typeVersion": 1.2,
      "position": [
        112,
        256
      ]
    },
    {
      "parameters": {
        "method": "POST",
        "url": "={{ $env.DATA_PIPELINE_URL || 'http://data-pipeline:8000' }}/run/ingest_nager",
        "options": {}
      },
      "id": "trigger-nager-ingestion",
      "name": "Trigger Nager Ingestion",
      "type": "n8n-nodes-base.httpRequest",
      "typeVersion": 4.2,
      "position": [
        336,
        256
      ]
    }
  ],
  "connections": {
    "Schedule Trigger": {
      "main": [
        [
          {
            "node": "Trigger Nager Ingestion",
            "type": "main",
            "index": 0
          }
        ]
      ]
    }
  },
  "active": false,
  "settings": {
    "executionOrder": "v1",
    "binaryMode": "separate"
  }
}
